.gitignore
CODE_OF_CONDUCT.md
LICENSE
README.md
requirements.txt
setup.py
.github/workflows/build.yml
.github/workflows/release.yml
circuitpython_build_tools/build.py
circuitpython_build_tools/target_versions.py
circuitpython_build_tools.egg-info/PKG-INFO
circuitpython_build_tools.egg-info/SOURCES.txt
circuitpython_build_tools.egg-info/dependency_links.txt
circuitpython_build_tools.egg-info/entry_points.txt
circuitpython_build_tools.egg-info/not-zip-safe
circuitpython_build_tools.egg-info/requires.txt
circuitpython_build_tools.egg-info/top_level.txt
circuitpython_build_tools/scripts/build_bundles.py
circuitpython_build_tools/scripts/build_mpy_cross.py
circuitpython_build_tools/scripts/circuitpython_mpy_cross.py