Metadata-Version: 2.4
Name: circuitpython-build-tools
Version: 1.18.1
Summary: CircuitPython library build tools
Home-page: https://www.adafruit.com/
Author: Scott Shawcroft
Author-email: scott@adafruit.com
Requires-Python: >=3.10
License-File: LICENSE
Requires-Dist: Click
Requires-Dist: requests
Requires-Dist: semver
Requires-Dist: tomli; python_version < "3.11"
Requires-Dist: platformdirs
Dynamic: author
Dynamic: author-email
Dynamic: home-page
Dynamic: license-file
Dynamic: requires-dist
Dynamic: requires-python
Dynamic: summary
